tsxv/__init__.py
tsxv/splitTrain.py
tsxv/splitTrainVal.py
tsxv/splitTrainValTest.py
timeseries_cv-0.1.5.dist-info/LICENSE.txt
timeseries_cv-0.1.5.dist-info/LICENSE
timeseries_cv-0.1.5.dist-info/WHEEL
timeseries_cv-0.1.5.dist-info/METADATA
timeseries_cv-0.1.5.dist-info/RECORD
