Metadata-Version: 2.1
Name: timeseries-cv
Version: 0.1.5
Summary: Timeseries cross-validation for Neural Networks
Home-page: https://github.com/DidierRLopes/timeseries-cv
License: MIT
Author: didier
Author-email: dro.lopes@campus.fct.unl.pt
Requires-Python: >=3.7,<4.0
Classifier: License :: OSI Approved :: MIT License
Classifier: Programming Language :: Python :: 3
Classifier: Programming Language :: Python :: 3.10
Classifier: Programming Language :: Python :: 3.7
Classifier: Programming Language :: Python :: 3.8
Classifier: Programming Language :: Python :: 3.9
Requires-Dist: numpy (>=1.21,<2.0)
Project-URL: Repository, https://github.com/DidierRLopes/timeseries-cv
